gyomu/__init__.py
gyomu/aes_encryption.py
gyomu/archive/__init__.py
gyomu/archive/zip.py
gyomu/base64.py
gyomu/common_status_code.py
gyomu/configurator.py
gyomu/db_connection_factory.py
gyomu/email_sender.py
gyomu/file_model.py
gyomu/file_operation.py
gyomu/gyomu_db_model.py
gyomu/holidays.py
gyomu/json.py
gyomu/milestone.py
gyomu/number_operation.py
gyomu/parameter_access.py
gyomu/process.py
gyomu/status_code.py
gyomu/task_operation.py
gyomu/tasks/__init__.py
gyomu/tasks/abstract_base_task.py
gyomu/tasks/delegate.py
gyomu/tasks/proposal.py
gyomu/tasks/simple.py
gyomu/user.py
gyomu/user_factory.py
gyomu/user_windows.py
gyomu/variable.py
gyomu-0.1.5a2.dist-info/LICENSE
gyomu-0.1.5a2.dist-info/WHEEL
gyomu-0.1.5a2.dist-info/METADATA
gyomu-0.1.5a2.dist-info/RECORD
