Metadata-Version: 2.1
Name: gyomu
Version: 0.1.5a2
Summary: Enterprise operational framework
Author: Yoshihisa Matsumoto
Author-email: yoshmatsumoto@gmail.com
Classifier: Programming Language :: Python :: 2
Classifier: Programming Language :: Python :: 2.7
Classifier: Programming Language :: Python :: 3
Classifier: Programming Language :: Python :: 3.4
Classifier: Programming Language :: Python :: 3.5
Classifier: Programming Language :: Python :: 3.6
Classifier: Programming Language :: Python :: 3.7
Classifier: Programming Language :: Python :: 3.8
Classifier: Programming Language :: Python :: 3.9
Requires-Dist: click (==7.1.2)
Requires-Dist: jsonpickle (==2.0.0)
Requires-Dist: jsons (==1.4.0)
Requires-Dist: pycryptodome (==3.10.1)
Requires-Dist: pyzipper (>=0.3.4,<0.4.0)
Requires-Dist: sqlalchemy (==1.4.00)
